setup.py
SKLogging/__init__.py
SKLogging.egg-info/PKG-INFO
SKLogging.egg-info/SOURCES.txt
SKLogging.egg-info/dependency_links.txt
SKLogging.egg-info/top_level.txt