Metadata-Version: 1.0
Name: SKLogging
Version: 3.6.1.2
Summary: Logging package for my personal use.
Home-page: UNKNOWN
Author: SuperKooks
Author-email: superkooks@superkooks.com
License: UNKNOWN
Platform: UNKNOWN
